pywsgiapp/WSGIApp.py
pywsgiapp/__init__.py
pywsgiapp/config/__init__.py
pywsgiapp/config/config.py
pywsgiapp/examples/__init__.py
pywsgiapp/examples/basic.py
pywsgiapp/examples/jsonresponse.py
pywsgiapp/examples/saveFile.py
pywsgiapp/support/__init__.py
pywsgiapp/support/parseEnviron.py
pywsgiapp/support/parseMultipartForm.py
pywsgiapp-0.0.5.dist-info/licenses/LICENSE
pywsgiapp-0.0.5.dist-info/METADATA
pywsgiapp-0.0.5.dist-info/WHEEL
pywsgiapp-0.0.5.dist-info/top_level.txt
pywsgiapp-0.0.5.dist-info/RECORD
