Metadata-Version: 2.4
Name: pywsgiapp
Version: 0.0.5
Summary: Bring Your Code to the Web with Ease using a Lightweight WSGI Application.
Home-page: https://github.com/jaythorat/pywsgiapp
Author: Jay Thorat
Author-email: dev.jaythorat@gmail.com
Classifier: Programming Language :: Python :: 3
Classifier: License :: OSI Approved :: MIT License
Classifier: Operating System :: OS Independent
Requires-Python: >=3.12
License-File: LICENSE
Requires-Dist: gunicorn>=23.0.0
Dynamic: author
Dynamic: author-email
Dynamic: classifier
Dynamic: description
Dynamic: description-content-type
Dynamic: home-page
Dynamic: license-file
Dynamic: requires-dist
Dynamic: requires-python
Dynamic: summary
